Metadata-Version: 2.1
Name: py-choria-discovery
Version: 0.1.0
Summary: A library for implementing Choria External Discovery in Python
Home-page: https://github.com/optiz0r/py-choria-discovery
Author: Ben Roberts
Author-email: me@benroberts.net
License: UNKNOWN
Platform: UNKNOWN
Classifier: Programming Language :: Python :: 2
Classifier: Programming Language :: Python :: 3
Classifier: License :: OSI Approved :: Apache Software License
Classifier: Operating System :: OS Independent
Requires-Python: >=2.6
